blueye/__init__.py
blueye/sdk/__init__.py
blueye/sdk/camera.py
blueye/sdk/constants.py
blueye/sdk/logs.py
blueye/sdk/motion.py
blueye/sdk/pioneer.py
blueye/sdk/utils.py
blueye.sdk_docs/404.html
blueye.sdk_docs/LICENSE
blueye.sdk_docs/README.html
blueye.sdk_docs/assets/fonts/font-awesome.css
blueye.sdk_docs/assets/fonts/material-icons.css
blueye.sdk_docs/assets/fonts/specimen/FontAwesome.ttf
blueye.sdk_docs/assets/fonts/specimen/FontAwesome.woff
blueye.sdk_docs/assets/fonts/specimen/FontAwesome.woff2
blueye.sdk_docs/assets/fonts/specimen/MaterialIcons-Regular.ttf
blueye.sdk_docs/assets/fonts/specimen/MaterialIcons-Regular.woff
blueye.sdk_docs/assets/fonts/specimen/MaterialIcons-Regular.woff2
blueye.sdk_docs/assets/images/favicon.png
blueye.sdk_docs/assets/images/icons/bitbucket.1b09e088.svg
blueye.sdk_docs/assets/images/icons/github.f0b8504a.svg
blueye.sdk_docs/assets/images/icons/gitlab.6dd19c00.svg
blueye.sdk_docs/assets/javascripts/application.c33a9706.js
blueye.sdk_docs/assets/javascripts/lunr/lunr.ar.js
blueye.sdk_docs/assets/javascripts/lunr/lunr.da.js
blueye.sdk_docs/assets/javascripts/lunr/lunr.de.js
blueye.sdk_docs/assets/javascripts/lunr/lunr.du.js
blueye.sdk_docs/assets/javascripts/lunr/lunr.es.js
blueye.sdk_docs/assets/javascripts/lunr/lunr.fi.js
blueye.sdk_docs/assets/javascripts/lunr/lunr.fr.js
blueye.sdk_docs/assets/javascripts/lunr/lunr.hu.js
blueye.sdk_docs/assets/javascripts/lunr/lunr.it.js
blueye.sdk_docs/assets/javascripts/lunr/lunr.ja.js
blueye.sdk_docs/assets/javascripts/lunr/lunr.jp.js
blueye.sdk_docs/assets/javascripts/lunr/lunr.multi.js
blueye.sdk_docs/assets/javascripts/lunr/lunr.nl.js
blueye.sdk_docs/assets/javascripts/lunr/lunr.no.js
blueye.sdk_docs/assets/javascripts/lunr/lunr.pt.js
blueye.sdk_docs/assets/javascripts/lunr/lunr.ro.js
blueye.sdk_docs/assets/javascripts/lunr/lunr.ru.js
blueye.sdk_docs/assets/javascripts/lunr/lunr.stemmer.support.js
blueye.sdk_docs/assets/javascripts/lunr/lunr.sv.js
blueye.sdk-5.0.1.dist-info/LICENSE
blueye.sdk-5.0.1.dist-info/WHEEL
blueye.sdk-5.0.1.dist-info/METADATA
blueye.sdk-5.0.1.dist-info/RECORD
