Metadata-Version: 2.1
Name: blueye.sdk
Version: 5.0.1
Summary: SDK for controlling a Blueye Pioneer
Home-page: https://www.blueyerobotics.com
Keywords: Blueye,Pioneer,Robotics,SDK,Software Development Kit
Author: Sindre Hansen
Author-email: sindre.hansen@blueye.no
Requires-Python: >=3.7,<4.0
Classifier: Programming Language :: Python :: 3
Classifier: Programming Language :: Python :: 3.7
Classifier: Programming Language :: Python :: 3.8
Provides-Extra: examples
Requires-Dist: asciimatics (>=1.11.0,<2.0.0); extra == "examples"
Requires-Dist: blueye.protocol (>=1.2.2,<2.0.0)
Requires-Dist: inputs (>=0.5,<0.6); extra == "examples"
Requires-Dist: matplotlib (>=3.1.1,<4.0.0); extra == "examples"
Requires-Dist: packaging (>=20.1,<21.0)
Requires-Dist: pandas (>=0.25.2,<0.26.0); extra == "examples"
Requires-Dist: requests (>=2.22.0,<3.0.0)
Requires-Dist: tabulate (>=0.8.5,<0.9.0)
Requires-Dist: webdavclient3 (>=0.12,<0.13); extra == "examples"
Project-URL: Repository, https://github.com/blueye-robotics/blueye.sdk
